doit_sqlite_sync.py
doit_sqlite_sync-1.0.dist-info/LICENSE
doit_sqlite_sync-1.0.dist-info/METADATA
doit_sqlite_sync-1.0.dist-info/WHEEL
doit_sqlite_sync-1.0.dist-info/entry_points.txt
doit_sqlite_sync-1.0.dist-info/top_level.txt
doit_sqlite_sync-1.0.dist-info/RECORD
